flask_bunnystream/__init__.py
flask_bunnystream/decorators.py
flask_bunnystream/events.py
flask_bunnystream/extension.py
flask_bunnystream-1.0.0.dist-info/licenses/LICENSE
flask_bunnystream-1.0.0.dist-info/METADATA
flask_bunnystream-1.0.0.dist-info/WHEEL
flask_bunnystream-1.0.0.dist-info/top_level.txt
flask_bunnystream-1.0.0.dist-info/RECORD
