Metadata-Version: 2.4
Name: flask-bunnystream
Version: 1.0.0
Summary: Flask extension for BunnyStream - Easy RabbitMQ integration with automatic connection management and event routing.
Author-email: Marc Ford <thenixninja@gmail.com>
Maintainer-email: Marc Ford <thenixninja@gmail.com>
License-Expression: GPL-3.0-or-later
Project-URL: Homepage, https://github.com/MarcFord/flask-bunnystream
Project-URL: Bug Reports, https://github.com/MarcFord/flask-bunnystream/issues
Project-URL: Source, https://github.com/MarcFord/flask-bunnystream
Project-URL: Documentation, https://github.com/MarcFord/flask-bunnystream#readme
Project-URL: Changelog, https://github.com/MarcFord/flask-bunnystream/blob/main/CHANGELOG.md
Keywords: rabbitmq,messaging,event-driven,message-broker,amqp,flask,bunnystream,pika
Classifier: Development Status :: 4 - Beta
Classifier: Intended Audience :: Developers
Classifier: Operating System :: OS Independent
Classifier: Programming Language :: Python :: 3.9
Classifier: Programming Language :: Python :: 3.10
Classifier: Programming Language :: Python :: 3.11
Classifier: Programming Language :: Python :: 3.12
Classifier: Framework :: Flask
Classifier: Topic :: Software Development :: Libraries :: Python Modules
Classifier: Topic :: System :: Networking
Classifier: Topic :: Communications
Requires-Python: >=3.8
License-File: LICENSE
Requires-Dist: bunnystream>=1.0.5
Requires-Dist: Flask>=2.0.0
Requires-Dist: user-agents>=2.0.0
Provides-Extra: test
Requires-Dist: pytest>=6.0; extra == "test"
Requires-Dist: pytest-cov<6.0,>=2.10; extra == "test"
Requires-Dist: pytest-mock<4.0,>=3.6; extra == "test"
Requires-Dist: pytest-xdist<4.0,>=2.0; extra == "test"
Provides-Extra: dev
Requires-Dist: black>=22.0; extra == "dev"
Requires-Dist: bandit>=1.7.0; extra == "dev"
Requires-Dist: safety>=2.0.0; extra == "dev"
Requires-Dist: pre-commit>=2.20.0; extra == "dev"
Provides-Extra: examples
Requires-Dist: flask-sqlalchemy>=3.0.0; extra == "examples"
Requires-Dist: sqlalchemy>=2.0.0; extra == "examples"
Requires-Dist: requests>=2.25.0; extra == "examples"
Dynamic: license-file
